{
    "generation": 5,
    "name": "Conkeldurr",
    "species": "Muscular Pok\u00e9mon",
    "height": "1.4\u00a0m (4\u203207\u2033)",
    "weight": "1.4\u00a0m (4\u203207\u2033)",
    "hp": 105,
    "attack": 140,
    "defense": 95,
    "speed": 45,
    "gender": {
        "male": "75%",
        "female": "25%"
    },
    "evolutions": {},
    "type": [
        "Fighting"
    ],
    "nationalNumber": 534,
    "specialName": null,
    "specialAbilities": [
        "Guts",
        "Sheer Force"
    ],
    "hiddenAbility": "Iron Fist",
    "specialAttack": 55,
    "specialDefense": 65,
    "catchRate": 45,
    "evYield": {
        "Attack": 3
    },
    "baseFriendship": 50,
    "baseExp": 227,
    "growthRate": "Medium Slow",
    "eggGroups": [
        "Human-Like"
    ],
    "eggCycles": 20,
    "movesLearnedAtLevel": {
        "Leer": 1,
        "Low Kick": 1,
        "Pound": 1,
        "Rock Throw": 1,
        "Focus Energy": 12,
        "Bulk Up": 16,
        "Rock Slide": 20,
        "Slam": 24,
        "Scary Face": 30,
        "Dynamic Punch": 36,
        "Hammer Arm": 42,
        "Stone Edge": 48,
        "Superpower": 54,
        "Focus Punch": 60
    },
    "movesLearnedOnEvolution": null,
    "movesLearnedByEggs": null,
    "movesLearnedByTutor": null,
    "movesLearnedByTm": {
        "Take Down": 1,
        "Scary Face": 6,
        "Protect": 7,
        "Low Kick": 12,
        "Thief": 18,
        "Facade": 25,
        "Bulldoze": 28,
        "Rock Tomb": 36,
        "Low Sweep": 39,
        "Fling": 43,
        "Endure": 47,
        "Sunny Day": 49,
        "Rain Dance": 50,
        "Dig": 55,
        "Brick Break": 58,
        "Bulk Up": 64,
        "Body Slam": 66,
        "Fire Punch": 67,
        "Thunder Punch": 68,
        "Ice Punch": 69,
        "Sleep Talk": 70,
        "Drain Punch": 73,
        "Rock Blast": 76,
        "Grass Knot": 81,
        "Poison Jab": 83,
        "Stomping Tantrum": 84,
        "Rest": 85,
        "Rock Slide": 86,
        "Taunt": 87,
        "Substitute": 103,
        "Helping Hand": 130,
        "Reversal": 134,
        "Earthquake": 149,
        "Stone Edge": 150,
        "Giga Impact": 152,
        "Focus Blast": 158,
        "Hyper Beam": 163,
        "Close Combat": 167,
        "Tera Blast": 171,
        "Smack Down": 179,
        "Knock Off": 181,
        "High Horsepower": 186,
        "Focus Punch": 192
    }
}