{
    "generation": 2,
    "name": "Hoppip",
    "species": "Cottonweed Pok\u00e9mon",
    "height": "0.4\u00a0m (1\u203204\u2033)",
    "weight": "0.4\u00a0m (1\u203204\u2033)",
    "hp": 35,
    "attack": 35,
    "defense": 40,
    "speed": 50,
    "gender": {
        "male": "50%",
        "female": "50%"
    },
    "evolutions": {},
    "type": [
        "Grass",
        "Flying"
    ],
    "nationalNumber": 187,
    "specialName": null,
    "specialAbilities": [
        "Chlorophyll",
        "Leaf Guard"
    ],
    "hiddenAbility": "Infiltrator",
    "specialAttack": 35,
    "specialDefense": 55,
    "catchRate": 255,
    "evYield": {
        "Sp. Def": 1
    },
    "baseFriendship": 50,
    "baseExp": 50,
    "growthRate": "Medium Slow",
    "eggGroups": [
        "Fairy",
        "Grass"
    ],
    "eggCycles": 20,
    "movesLearnedAtLevel": {
        "Splash": 1,
        "Tackle": 1,
        "Tail Whip": 4,
        "Absorb": 6,
        "Fairy Wind": 8,
        "Poison Powder": 10,
        "Sleep Powder": 10,
        "Stun Spore": 10,
        "Bullet Seed": 12,
        "Synthesis": 15,
        "Leech Seed": 19,
        "Mega Drain": 22,
        "Acrobatics": 24,
        "Cotton Spore": 27,
        "U-turn": 29,
        "Giga Drain": 32,
        "Bounce": 35,
        "Memento": 38
    },
    "movesLearnedOnEvolution": null,
    "movesLearnedByEggs": null,
    "movesLearnedByTutor": null,
    "movesLearnedByTm": {
        "Take Down": 1,
        "Charm": 2,
        "Protect": 7,
        "Acrobatics": 14,
        "Thief": 18,
        "Trailblaze": 20,
        "Facade": 25,
        "Aerial Ace": 27,
        "Magical Leaf": 33,
        "Fling": 43,
        "Endure": 47,
        "Sunny Day": 49,
        "Rain Dance": 50,
        "Bullet Seed": 56,
        "U-turn": 60,
        "Sleep Talk": 70,
        "Seed Bomb": 71,
        "Reflect": 74,
        "Light Screen": 75,
        "Dazzling Gleam": 79,
        "Grass Knot": 81,
        "Rest": 85,
        "Swords Dance": 88,
        "Substitute": 103,
        "Giga Drain": 111,
        "Tailwind": 113,
        "Energy Ball": 119,
        "Encore": 122,
        "Helping Hand": 130,
        "Pollen Puff": 131,
        "Baton Pass": 132,
        "Grassy Terrain": 137,
        "Leaf Storm": 159,
        "Solar Beam": 168,
        "Tera Blast": 171
    }
}