{
    "generation": 3,
    "name": "Sableye",
    "species": "Darkness Pok\u00e9mon",
    "height": "0.5\u00a0m (1\u203208\u2033)",
    "weight": "0.5\u00a0m (1\u203208\u2033)",
    "hp": 50,
    "attack": 85,
    "defense": 125,
    "speed": 20,
    "gender": {
        "male": "50%",
        "female": "50%"
    },
    "evolutions": {},
    "type": [
        "Dark",
        "Ghost"
    ],
    "nationalNumber": 302,
    "specialName": "Mega Sableye",
    "specialAbilities": [
        "Magic Bounce"
    ],
    "hiddenAbility": null,
    "specialAttack": 85,
    "specialDefense": 115,
    "catchRate": 45,
    "evYield": {
        "Attack": 1,
        "Defense": 1
    },
    "baseFriendship": 35,
    "baseExp": 168,
    "growthRate": "Medium Slow",
    "eggGroups": [
        "Human-Like"
    ],
    "eggCycles": 25,
    "movesLearnedAtLevel": {
        "Leer": 1,
        "Scratch": 1,
        "Astonish": 3,
        "Shadow Sneak": 9,
        "Fake Out": 12,
        "Disable": 15,
        "Detect": 18,
        "Night Shade": 21,
        "Fury Swipes": 24,
        "Knock Off": 27,
        "Quash": 30,
        "Shadow Claw": 33,
        "Mean Look": 36,
        "Power Gem": 39,
        "Zen Headbutt": 42,
        "Shadow Ball": 45,
        "Foul Play": 48
    },
    "movesLearnedOnEvolution": null,
    "movesLearnedByEggs": null,
    "movesLearnedByTutor": null,
    "movesLearnedByTm": {
        "Take Down": 1,
        "Mud-Slap": 5,
        "Protect": 7,
        "Low Kick": 12,
        "Psybeam": 16,
        "Confuse Ray": 17,
        "Thief": 18,
        "Facade": 25,
        "Aerial Ace": 27,
        "Hex": 29,
        "Snarl": 30,
        "Metal Claw": 31,
        "Icy Wind": 34,
        "Mud Shot": 35,
        "Rock Tomb": 36,
        "Low Sweep": 39,
        "Night Shade": 42,
        "Fling": 43,
        "Endure": 47,
        "Sunny Day": 49,
        "Rain Dance": 50,
        "Dig": 55,
        "Brick Break": 58,
        "Zen Headbutt": 59,
        "Shadow Claw": 61,
        "Foul Play": 62,
        "Bulk Up": 64,
        "Body Slam": 66,
        "Fire Punch": 67,
        "Thunder Punch": 68,
        "Ice Punch": 69,
        "Sleep Talk": 70,
        "Drain Punch": 73,
        "Reflect": 74,
        "Light Screen": 75,
        "Dazzling Gleam": 79,
        "Metronome": 80,
        "Thunder Wave": 82,
        "Poison Jab": 83,
        "Rest": 85,
        "Taunt": 87,
        "Imprison": 92,
        "Dark Pulse": 94,
        "Skill Swap": 98,
        "Power Gem": 101,
        "Substitute": 103,
        "X-Scissor": 105,
        "Will-O-Wisp": 107,
        "Trick": 109,
        "Giga Drain": 111,
        "Shadow Ball": 114,
        "Energy Ball": 119,
        "Psychic": 120,
        "Encore": 122,
        "Calm Mind": 129,
        "Helping Hand": 130,
        "Nasty Plot": 140,
        "Phantom Force": 151,
        "Giga Impact": 152,
        "Hyper Beam": 163,
        "Tera Blast": 171
    }
}