{
    "generation": 3,
    "name": "Solrock",
    "species": "Meteorite Pok\u00e9mon",
    "height": "1.2\u00a0m (3\u203211\u2033)",
    "weight": "1.2\u00a0m (3\u203211\u2033)",
    "hp": 90,
    "attack": 95,
    "defense": 85,
    "speed": 70,
    "gender": null,
    "evolutions": {},
    "type": [
        "Rock",
        "Psychic"
    ],
    "nationalNumber": 338,
    "specialName": null,
    "specialAbilities": [
        "Levitate"
    ],
    "hiddenAbility": null,
    "specialAttack": 55,
    "specialDefense": 65,
    "catchRate": 45,
    "evYield": {
        "Attack": 2
    },
    "baseFriendship": 50,
    "baseExp": 161,
    "growthRate": "Fast",
    "eggGroups": [
        "Mineral"
    ],
    "eggCycles": 25,
    "movesLearnedAtLevel": {
        "Confusion": 1,
        "Flare Blitz": 1,
        "Harden": 1,
        "Morning Sun": 1,
        "Rock Throw": 1,
        "Tackle": 1,
        "Hypnosis": 5,
        "Rock Polish": 10,
        "Rock Slide": 15,
        "Zen Headbutt": 20,
        "Cosmic Power": 25,
        "Psychic": 30,
        "Stone Edge": 35,
        "Solar Beam": 40,
        "Wonder Room": 45,
        "Explosion": 50
    },
    "movesLearnedOnEvolution": null,
    "movesLearnedByEggs": null,
    "movesLearnedByTutor": null,
    "movesLearnedByTm": {
        "Calm Mind": 4,
        "Sunny Day": 11,
        "Hyper Beam": 15,
        "Light Screen": 16,
        "Protect": 17,
        "Rain Dance": 18,
        "Safeguard": 20,
        "Solar Beam": 22,
        "Earthquake": 26,
        "Psychic": 29,
        "Shadow Ball": 30,
        "Double Team": 32,
        "Reflect": 33,
        "Flamethrower": 35,
        "Sandstorm": 37,
        "Fire Blast": 38,
        "Rock Tomb": 39,
        "Facade": 42,
        "Rest": 44,
        "Skill Swap": 48,
        "Overheat": 50,
        "Charge Beam": 57,
        "Endure": 58,
        "Will-O-Wisp": 61,
        "Explosion": 64,
        "Recycle": 67,
        "Giga Impact": 68,
        "Rock Polish": 69,
        "Flash": 70,
        "Stone Edge": 71,
        "Gyro Ball": 74,
        "Swords Dance": 75,
        "Stealth Rock": 76,
        "Psych Up": 77,
        "Rock Slide": 80,
        "Sleep Talk": 82,
        "Bulldoze": 83,
        "Dream Eater": 85,
        "Grass Knot": 86,
        "Swagger": 87,
        "Substitute": 90,
        "Trick Room": 92
    }
}