{
    "generation": 4,
    "name": "Abomasnow",
    "species": "Frost Tree Pok\u00e9mon",
    "height": "2.2\u00a0m (7\u203203\u2033)",
    "weight": "2.2\u00a0m (7\u203203\u2033)",
    "hp": 90,
    "attack": 92,
    "defense": 75,
    "speed": 60,
    "gender": {
        "male": "50%",
        "female": "50%"
    },
    "evolutions": {},
    "type": [
        "Grass",
        "Ice"
    ],
    "nationalNumber": 460,
    "specialName": null,
    "specialAbilities": [
        "Snow Warning"
    ],
    "hiddenAbility": "Soundproof",
    "specialAttack": 92,
    "specialDefense": 85,
    "catchRate": 60,
    "evYield": {
        "Attack": 1,
        "Sp. Atk": 1
    },
    "baseFriendship": 50,
    "baseExp": 173,
    "growthRate": "Slow",
    "eggGroups": [
        "Grass",
        "Monster"
    ],
    "eggCycles": 20,
    "movesLearnedAtLevel": {
        "Aurora Veil": 1,
        "Leafage": 1,
        "Leer": 1,
        "Mist": 1,
        "Powder Snow": 1,
        "Ice Shard": 15,
        "Razor Leaf": 20,
        "Icy Wind": 25,
        "Swagger": 30,
        "Ingrain": 35,
        "Wood Hammer": 43,
        "Blizzard": 49,
        "Sheer Cold": 56
    },
    "movesLearnedOnEvolution": [
        "Ice Punch"
    ],
    "movesLearnedByEggs": null,
    "movesLearnedByTutor": null,
    "movesLearnedByTm": {
        "Take Down": 1,
        "Mud-Slap": 5,
        "Scary Face": 6,
        "Protect": 7,
        "Water Pulse": 11,
        "Low Kick": 12,
        "Trailblaze": 20,
        "Chilling Water": 22,
        "Facade": 25,
        "Bulldoze": 28,
        "Magical Leaf": 33,
        "Icy Wind": 34,
        "Rock Tomb": 36,
        "Fling": 43,
        "Avalanche": 46,
        "Endure": 47,
        "Rain Dance": 50,
        "Snowscape": 52,
        "Bullet Seed": 56,
        "Brick Break": 58,
        "Body Slam": 66,
        "Ice Punch": 69,
        "Sleep Talk": 70,
        "Seed Bomb": 71,
        "Grass Knot": 81,
        "Stomping Tantrum": 84,
        "Rest": 85,
        "Rock Slide": 86,
        "Swords Dance": 88,
        "Body Press": 89,
        "Substitute": 103,
        "Giga Drain": 111,
        "Energy Ball": 119,
        "Ice Spinner": 124,
        "Helping Hand": 130,
        "Earth Power": 133,
        "Ice Beam": 135,
        "Blizzard": 143,
        "Earthquake": 149,
        "Giga Impact": 152,
        "Outrage": 156,
        "Focus Blast": 158,
        "Leaf Storm": 159,
        "Hyper Beam": 163,
        "Solar Beam": 168,
        "Tera Blast": 171
    }
}