{
    "generation": 8,
    "name": "Glastrier",
    "species": "Wild Horse Pok\u00e9mon",
    "height": "2.2\u00a0m (7\u203203\u2033)",
    "weight": "2.2\u00a0m (7\u203203\u2033)",
    "hp": 100,
    "attack": 145,
    "defense": 130,
    "speed": 30,
    "gender": null,
    "evolutions": {},
    "type": [
        "Ice"
    ],
    "nationalNumber": 896,
    "specialName": null,
    "specialAbilities": [
        "Chilling Neigh"
    ],
    "hiddenAbility": null,
    "specialAttack": 65,
    "specialDefense": 110,
    "catchRate": 3,
    "evYield": {
        "Attack": 3
    },
    "baseFriendship": 35,
    "baseExp": 290,
    "growthRate": "Slow",
    "eggGroups": [
        "Undiscovered"
    ],
    "eggCycles": 120,
    "movesLearnedAtLevel": {
        "Tackle": 1,
        "Tail Whip": 1,
        "Double Kick": 6,
        "Avalanche": 12,
        "Stomp": 18,
        "Torment": 24,
        "Mist": 30,
        "Icicle Crash": 36,
        "Take Down": 42,
        "Iron Defense": 48,
        "Thrash": 54,
        "Taunt": 60,
        "Double-Edge": 66,
        "Swords Dance": 72
    },
    "movesLearnedOnEvolution": null,
    "movesLearnedByEggs": null,
    "movesLearnedByTutor": null,
    "movesLearnedByTm": {
        "Take Down": 1,
        "Scary Face": 6,
        "Protect": 7,
        "Trailblaze": 20,
        "Facade": 25,
        "Bulldoze": 28,
        "Snarl": 30,
        "Icy Wind": 34,
        "Mud Shot": 35,
        "Avalanche": 46,
        "Endure": 47,
        "Snowscape": 52,
        "Smart Strike": 53,
        "Zen Headbutt": 59,
        "Body Slam": 66,
        "Sleep Talk": 70,
        "Stomping Tantrum": 84,
        "Rest": 85,
        "Taunt": 87,
        "Swords Dance": 88,
        "Body Press": 89,
        "Substitute": 103,
        "Iron Defense": 104,
        "Crunch": 108,
        "Heavy Slam": 121,
        "Ice Beam": 135,
        "Blizzard": 143,
        "Giga Impact": 152,
        "Outrage": 156,
        "Hyper Beam": 163,
        "Close Combat": 167,
        "Tera Blast": 171
    }
}