{
    "generation": 1,
    "name": "Wartortle",
    "species": "Turtle Pok\u00e9mon",
    "height": "1.0\u00a0m (3\u203203\u2033)",
    "weight": "1.0\u00a0m (3\u203203\u2033)",
    "hp": 59,
    "attack": 63,
    "defense": 80,
    "speed": 58,
    "gender": {
        "male": "87.5%",
        "female": "12.5%"
    },
    "evolutions": {
        "BLASTOISE": {
            "level": 36,
            "time": null,
            "heldItem": null,
            "usedItem": null,
            "hasPokemon": null,
            "highFriendship": null,
            "needsTrade": null,
            "usedMove": null,
            "learnedMove": null
        }
    },
    "type": [
        "Water"
    ],
    "nationalNumber": 8,
    "specialName": null,
    "specialAbilities": [
        "Torrent"
    ],
    "hiddenAbility": "Rain Dish",
    "specialAttack": 65,
    "specialDefense": 80,
    "catchRate": 45,
    "evYield": {
        "Defense": 1,
        "Sp. Def": 1
    },
    "baseFriendship": 50,
    "baseExp": 142,
    "growthRate": "Medium Slow",
    "eggGroups": [
        "Monster",
        "Water 1"
    ],
    "eggCycles": 20,
    "movesLearnedAtLevel": {
        "Tackle": 1,
        "Tail Whip": 1,
        "Water Gun": 1,
        "Withdraw": 1,
        "Rapid Spin": 9,
        "Bite": 12,
        "Water Pulse": 15,
        "Protect": 20,
        "Rain Dance": 25,
        "Aqua Tail": 30,
        "Shell Smash": 35,
        "Iron Defense": 40,
        "Hydro Pump": 45,
        "Skull Bash": 50
    },
    "movesLearnedOnEvolution": null,
    "movesLearnedByEggs": null,
    "movesLearnedByTutor": null,
    "movesLearnedByTm": {
        "Focus Punch": 1,
        "Water Pulse": 3,
        "Hail": 7,
        "Work Up": 10,
        "Ice Beam": 13,
        "Blizzard": 14,
        "Protect": 17,
        "Rain Dance": 18,
        "Iron Tail": 23,
        "Dig": 28,
        "Brick Break": 31,
        "Double Team": 32,
        "Rock Tomb": 39,
        "Facade": 42,
        "Rest": 44,
        "Attract": 45,
        "Scald": 49,
        "False Swipe": 54,
        "Brine": 55,
        "Fling": 56,
        "Endure": 58,
        "Dragon Pulse": 59,
        "Gyro Ball": 74,
        "Sleep Talk": 82,
        "Swagger": 87,
        "Substitute": 90,
        "Surf": 95,
        "Strength": 96,
        "Rock Smash": 98,
        "Waterfall": 99
    }
}